sklearn11/__init__.py
sklearn11/sklearn11.py
sklearn11-0.0.6.dist-info/METADATA
sklearn11-0.0.6.dist-info/WHEEL
sklearn11-0.0.6.dist-info/top_level.txt
sklearn11-0.0.6.dist-info/RECORD
