Metadata-Version: 2.2
Name: sklearn11
Version: 0.0.6
Summary: 100 alcaz
Home-page: https://github.com/ozbere31/sklearn11
Author: olcay
Author-email: olcay.aydn25@gmail.com
Classifier: Programming Language :: Python :: 3.9
Classifier: License :: OSI Approved :: MIT License
Classifier: Operating System :: OS Independent
Requires-Python: >=3
Dynamic: author
Dynamic: author-email
Dynamic: classifier
Dynamic: description-content-type
Dynamic: home-page
Dynamic: requires-python
Dynamic: summary
